tmp_connection_psql/__init__.py
tmp_connection_psql/tmp_connection_psql.py
tmp_connection_psql-1.3.0.dist-info/LICENSE.md
tmp_connection_psql-1.3.0.dist-info/WHEEL
tmp_connection_psql-1.3.0.dist-info/METADATA
tmp_connection_psql-1.3.0.dist-info/RECORD
