Metadata-Version: 2.1
Name: tmp-connection-psql
Version: 1.3.0
Summary: Little project to create a temparory connection to a psql database
Home-page: https://gitlab.obspm.fr/uchosson/tmp_connection_psql
License: EUPL v1.2
Author: CHOSSON Ulysse
Author-email: ulysse.chosson@obspm.fr
Requires-Python: >=3.10,<4.0.0
Classifier: License :: Other/Proprietary License
Classifier: Programming Language :: Python :: 3
Classifier: Programming Language :: Python :: 3.10
Classifier: Programming Language :: Python :: 3.11
Requires-Dist: psycopg (>=3.1.4,<4.0.0)
Requires-Dist: pytest-postgresql (>=4.1.1,<5.0.0)
Project-URL: Repository, https://gitlab.obspm.fr/uchosson/tmp_connection_psql
